{
  "name": {
    "en": "Theerachot Hengsimmakourup",
    "th": "ธีรโชติ เฮงสิมมาเคารพ"
  },
  "title": {
    "en": "IT Management Process Engineer & Cybersecurity Specialist",
    "th": "วิศวกรกระบวนการจัดการไอทีและผู้เชี่ยวชาญด้านความปลอดภัยทางไซเบอร์"
  },
  "location": {
    "en": "Bangkok, Thailand",
    "th": "กรุงเทพมหานคร, ประเทศไทย"
  },
  "address": {
    "en": "83 Soi Saksin, Khlong San Subdistrict, Khlong San District, Bangkok 10600",
    "th": "83 ซอยศักดิ์สิน แขวงคลองสาน เขตคลองสาน กรุงเทพมหานคร 10600"
  },
  "birthday": "18 July 1995",
  "age": "30",
  "summary": {
    "en": "IT Management Process and Cybersecurity Specialist with over 6 years of experience in managing IT Infrastructure, Network Engineering, and Security Operations for banking organizations. Expertise in Event Management according to ITIL v4, AI data analytics, and automation development to optimize operational efficiency.",
    "th": "ผู้เชี่ยวชาญด้าน IT Management Process และ Cybersecurity ด้วยประสบการณ์กว่า 6 ปีในการบริหารจัดการระบบ IT Infrastructure, Network Engineering, และ Security Operations สำหรับองค์กรธนาคาร. มีความชำนาญในการจัดการ Event Management ตาม ITIL v4, การวิเคราะห์ข้อมูลด้วย AI, และการพัฒนาระบบอัตโนมัติเพื่อเพิ่มประสิทธิภาพการทำงาน."
  },
  "skills": {
    "Presale & Sales": [
      {
        "en": "Customer Requirement Analysis",
        "th": "ศึกษาความต้องการลูกค้า"
      },
      {
        "en": "Solution Presentation",
        "th": "นำเสนอโซลูชัน (Presentation)"
      },
      {
        "en": "Initial Implementation Planning",
        "th": "วางแผนการติดตั้งระบบเบื้องต้น"
      },
      {
        "en": "Preliminary Lab Testing",
        "th": "ทดสอบระบบเบื้องต้น (Lab Test)"
      },
      {
        "en": "Basic Documentation & POC",
        "th": "จัดทำเอกสารและ Proof of Concept เบื้องต้น"
      }
    ],
    "IT Management": [
      {
        "en": "ITIL v4 Event/Incident/Change Management",
        "th": "การจัดการ Event/Incident/Change ตาม ITIL v4"
      },
      {
        "en": "IT Operations & Asset Management",
        "th": "การดำเนินงานด้านไอทีและการจัดการสินทรัพย์"
      },
      {
        "en": "Vendor & Cost Management",
        "th": "การจัดการผู้ขายและต้นทุน"
      },
      {
        "en": "Project Management",
        "th": "การบริหารจัดการโครงการ"
      },
      {
        "en": "Process Optimization",
        "th": "การเพิ่มประสิทธิภาพกระบวนการ"
      }
    ],
    "Cybersecurity": [
      {
        "en": "CrowdStrike EDR Administration",
        "th": "การบริหารจัดการ CrowdStrike EDR"
      },
      {
        "en": "Palo Alto Networks Firewall",
        "th": "Palo Alto Networks Firewall"
      },
      {
        "en": "Network Security Monitoring",
        "th": "การตรวจสอบความปลอดภัยเครือข่าย"
      },
      {
        "en": "Forensics Investigation",
        "th": "การสืบสวนทางนิติดิจิทัล (Forensics)"
      },
      {
        "en": "Threat Detection & Response",
        "th": "การตรวจจับและตอบสนองต่อภัยคุกคาม"
      },
      {
        "en": "Vulnerability Assessment & Response",
        "th": "การประเมินความเสี่ยงและตอบสนอง (VA & Response)"
      },
      {
        "en": "VA Automation & SIEM Data Integration",
        "th": "VA Automation และการจัดการข้อมูล SIEM"
      },
      {
        "en": "EDR Rules & Alert Testing",
        "th": "การจัดการกฎ EDR และทดสอบ Alert (Discovery/Inventory)"
      },
      {
        "en": "Pipeline Contracts & Artifact Registry",
        "th": "กำหนด Contract (Inputs/Outputs) และ Artifact Registry"
      },
      {
        "en": "API Mapping (RTR Admin/Batch)",
        "th": "การเชื่อมต่อ API (RTR Admin/Batch)"
      },
      {
        "en": "Playbook Engineering & Security Guardrails",
        "th": "พัฒนา Playbook และ Security Guards (Allowlist/Checksum)"
      },
      {
        "en": "Deployment Strategy (Staging/UAT to Cutover)",
        "th": "กลยุทธ์การ Deployment (Staging/UAT -> Parallel Run -> Cutover)"
      },
      {
        "en": "Operations (Monitor/Tune & Decommission/Rollback)",
        "th": "การปฏิบัติการ (Monitor/Tune และ Decommission/Rollback)"
      }
    ],
    "Network & Infrastructure": [
      {
        "en": "Network Engineering",
        "th": "วิศวกรรมเครือข่าย"
      },
      {
        "en": "Fortigate Firewall Administration",
        "th": "การบริหารจัดการ Fortigate Firewall"
      },
      {
        "en": "Network Monitoring (SolarWinds, Sitescope)",
        "th": "การตรวจสอบเครือข่าย (SolarWinds, Sitescope)"
      },
      {
        "en": "OpenWrt/hostapd Configuration",
        "th": "การตั้งค่า OpenWrt/hostapd"
      },
      {
        "en": "FreeRADIUS Administration",
        "th": "การบริหารจัดการ FreeRADIUS"
      }
    ],
    "Automation & Analytics": [
      {
        "en": "Excel VBA & Power Automate",
        "th": "Excel VBA และ Power Automate"
      },
      {
        "en": "Power BI Data Analysis",
        "th": "การวิเคราะห์ข้อมูลด้วย Power BI"
      },
      {
        "en": "AI Prompt Engineering",
        "th": "วิศวกรรมคำสั่ง AI (Prompt Engineering)"
      },
      {
        "en": "n8n Workflow Automation",
        "th": "ระบบอัตโนมัติด้วย n8n"
      },
      {
        "en": "Python Scripting",
        "th": "การเขียนสคริปต์ Python"
      }
    ],
    "Tools & Platforms": [
      {
        "en": "SolarWinds, Sitescope, PagerDuty, Splunk",
        "th": "SolarWinds, Sitescope, PagerDuty, Splunk"
      },
      {
        "en": "CrowdStrike Falcon, Palo Alto PAN-OS",
        "th": "CrowdStrike Falcon, Palo Alto PAN-OS"
      },
      {
        "en": "Microsoft 365, Google Workspace, Lark",
        "th": "Microsoft 365, Google Workspace, Lark"
      },
      {
        "en": "Grafana, InfluxDB, Prometheus",
        "th": "Grafana, InfluxDB, Prometheus"
      }
    ]
  },
  "social": {
    "email": "Theerachot.si.61@ubu.ac.th",
    "phone": "061-0784261",
    "line": "ddc_777",
    "linkedin": "https://www.linkedin.com/in/theeraochot-hangsimmakourop-5463552aa",
    "github": "https://github.com/armkong33120"
  }
}